gameauth/__init__.py
gameauth/__main__.py
gameauth/key_util.py
gameauth/password.py
gameauth/token.py
gameauth/token_generator.py
gameauth/token_validator.py
gamecomm/__init__.py
gamecomm/client/__init__.py
gamecomm/client/game_client.py
gamecomm/client/game_connection.py
gamecomm/client/tcp_connection.py
gamecomm/client/ws_connection.py
gamecomm/server/__init__.py
gamecomm/server/game_connection.py
gamecomm/server/tcp_listener.py
gamecomm/server/ws_listener.py
gamedb/__init__.py
gamedb/game_repository.py
gamedb/user_repository.py
gamedb/json/__init__.py
gamedb/json/game_repository.py
gamedb/json/json_db.py
gamedb/json/user_repository.py
gamedb/mongo/__init__.py
gamedb/mongo/game_repository.py
gamedb/mongo/user_repository.py
vtece4564_gamelib-0.1.9.dist-info/LICENSE
vtece4564_gamelib-0.1.9.dist-info/METADATA
vtece4564_gamelib-0.1.9.dist-info/WHEEL
vtece4564_gamelib-0.1.9.dist-info/top_level.txt
vtece4564_gamelib-0.1.9.dist-info/RECORD
