Metadata-Version: 2.1
Name: vtece4564-gamelib
Version: 0.1.9
Summary: A support library for the ECE 4564 Final Project
Author: Carl Harris
License: Copyright (c) 2022-2023 Virginia Polytechnic Institute and State University
Requires-Python: >=3.10
License-File: LICENSE
Requires-Dist: cryptography ==43.0.3
Requires-Dist: pyjwt ==2.9.0
Requires-Dist: pymongo ==4.10.1
Requires-Dist: websockets ==11.0.3
Requires-Dist: py-purecrypt ==0.1.1
